[
    {
        "time": "2026-04-02 11:34:25",
        "category": "repair",
        "files": [
            "GIS_690218.xlsx"
        ],
        "count": 1
    },
    {
        "time": "2026-04-02 11:46:49",
        "category": "pressure",
        "files": [
            "PRESSURE_กบินทร์บุรี_ปีงบ69.xlsx",
            "PRESSURE_ขลุง_ปีงบ69.xlsx",
            "PRESSURE_คลองใหญ่_ปีงบ69.xlsx",
            "PRESSURE_จันทบุรี_ปีงบ69.xlsx",
            "PRESSURE_ฉะเชิงเทรา_ปีงบ69.xlsx",
            "PRESSURE_ชลบุรี_ปีงบ69.xlsx",
            "PRESSURE_ตราด_ปีงบ69.xlsx",
            "PRESSURE_บางคล้า_ปีงบ69.xlsx",
            "PRESSURE_บางปะกง_ปีงบ69.xlsx",
            "PRESSURE_บ้านฉาง_ปีงบ69.xlsx",
            "PRESSURE_บ้านบึง_ปีงบ69.xlsx",
            "PRESSURE_ปราจีนบุรี_ปีงบ69.xlsx",
            "PRESSURE_ปากน้ำประแสร์_ปีงบ69.xlsx",
            "PRESSURE_พนมสารคาม_ปีงบ69.xlsx",
            "PRESSURE_พนัสนิคม_ปีงบ69.xlsx",
            "PRESSURE_พัทยา_ปีงบ69.xlsx",
            "PRESSURE_ระยอง_ปีงบ69.xlsx",
            "PRESSURE_วัฒนานคร_ปีงบ69.xlsx",
            "PRESSURE_ศรีราชา_ปีงบ69.xlsx",
            "PRESSURE_สระแก้ว_ปีงบ69.xlsx",
            "PRESSURE_อรัญประเทศ_ปีงบ69.xlsx",
            "PRESSURE_แหลมฉบัง_ปีงบ69.xlsx"
        ],
        "count": 22
    },
    {
        "time": "2026-04-04 04:28:45",
        "category": "pending",
        "files": [
            "ค้างซ่อม_11-68.xlsx",
            "ค้างซ่อม_12-68.xlsx",
            "ค้างซ่อม_10-68.xlsx",
            "ค้างซ่อม_01-69.xlsx"
        ],
        "count": 4
    },
    {
        "time": "2026-04-04 04:30:25",
        "category": "pending",
        "files": [
            "ค้างซ่อม_02-69.xlsx",
            "ค้างซ่อม_03-69.xlsx",
            "ค้างซ่อม_04-69.xlsx"
        ],
        "count": 3
    }
]