{"mtime":1775223380,"data":[{"n":"P3-หมู่บ้านสวนวิวเขา","p":0.35,"a":0,"h":[null,null,null,null,null,null,null,null,null,null,null,null,null,null,null,null,null,null,null,null,null,null,null,null]},{"n":"P3-หมู่บ้านพฤษชาติ 2","p":0.27,"a":0,"h":[null,null,null,null,null,null,null,null,null,null,null,null,null,null,null,null,null,null,null,null,null,null,null,null]},{"n":"P3-MM-01-2-ทางรถไฟแหลมฉบัง","p":1.84,"a":0,"h":[null,null,null,null,null,null,null,null,null,null,null,null,null,null,null,null,null,null,null,null,null,null,null,null]},{"n":"P3-บูสเตอร์ปั้มใหม่ จ่ายเก้ากิโล","p":null,"a":0,"h":[null,null,null,null,null,null,null,null,null,null,null,null,null,null,null,null,null,null,null,null,null,null,null,null]},{"n":"P3-MM-01-4-ลงอ่าวอุดม","p":1.9,"a":2.16,"h":[2.47,2.93,3.17,3.24,3.07,2.55,1.81,1.67,1.87,1.98,2.14,2.25,2.3,2.22,2.31,2.32,2.14,1.86,1.6,1.51,1.45,1.46,1.52,1.88]},{"n":"P3-MM-02-1-จุกเฌอ","p":1.73,"a":0,"h":[null,null,null,null,null,null,null,null,null,null,null,null,null,null,null,null,null,null,null,null,null,null,null,null]},{"n":"P3-MM-02-2-ชุมชนหนองคล้าใหม่","p":1.7,"a":1.75,"h":[2,2.35,2.56,2.59,2.35,1.88,1.12,1.17,1.33,1.35,1.43,1.8,1.84,2,2.12,2.21,2.06,1.66,1.31,1.3,1.27,1.23,1.47,1.69]},{"n":"P3-MM-02-3-สี่แยกสาธารณสุข","p":1.73,"a":1.78,"h":[1.59,1.7,1.84,1.98,2.09,2.11,1.94,1.68,1.62,1.62,1.63,1.68,1.74,1.8,1.87,1.94,1.99,2,1.86,1.72,1.65,1.57,1.56,1.59]},{"n":"P3-Village hill","p":0.73,"a":0,"h":[-0.01,0,0,0,0,0,0,0,0,0,0,0,0,-0.01,-0.01,-0.01,0,-0.01,0,-0.01,-0.01,0,0,-0.01]},{"n":"P3-Temporary SR","p":1.87,"a":0,"h":[null,null,null,null,null,null,null,null,null,null,null,null,null,null,null,null,null,null,null,null,null,null,null,null]},{"n":"P3-MM-13-1-บ้านนาเก่า","p":2.43,"a":0,"h":[null,null,null,null,null,null,null,null,null,null,null,null,null,null,null,null,null,null,null,null,null,null,null,null]},{"n":"P3-MM-13-2-เคหะ","p":2.16,"a":0,"h":[null,null,null,null,null,null,null,null,null,null,null,null,null,null,null,null,null,null,null,null,null,null,null,null]},{"n":"P3-MM-15-2-ตลาดวรกิจบึง","p":1.37,"a":1.08,"h":[1.41,1.54,1.56,1.52,0.85,0.8,0.81,0.77,0.93,0.96,1,1.04,1.12,1.2,1.25,1.24,1.19,1.03,0.87,0.87,0.88,0.84,0.96,1.23]},{"n":"P3-MM-15-4-หน้าวัดหนองมะนาว","p":0.37,"a":0.23,"h":[0.99,1.27,1.21,1.06,0.4,0.07,0,0,0,0,0,0,0,0.05,0.13,0.11,0.01,0,0,0,0,0,0.01,0.31]}]}